pretty_build.py
textual_tui.py
pretty_build-1.2.8.data/data/share/pretty-build/config/.pretty_build.conf.example
pretty_build-1.2.8.data/data/share/pretty-build/docs/INSTALL_GUIDE.md
pretty_build-1.2.8.data/data/share/pretty-build/docs/TEXTUAL_QUICKSTART.md
pretty_build-1.2.8.data/data/share/pretty-build/docs/TUI_README.md
pretty_build-1.2.8.data/data/share/pretty-build/docs/USAGE_GUIDE.md
pretty_build-1.2.8.data/data/share/pretty-build/examples/demo.py
pretty_build-1.2.8.data/data/share/pretty-build/examples/demo_tui.py
pretty_build-1.2.8.data/data/share/pretty-build/examples/tests/test_textual_tui.py
pretty_build-1.2.8.data/data/share/pretty-build/examples/tests/test_tui_buttons.py
pretty_build-1.2.8.data/data/share/pretty-build/scripts/start.bat
pretty_build-1.2.8.data/data/share/pretty-build/scripts/start.sh
pretty_build-1.2.8.data/data/share/pretty-build/templates/stm32f103c8t6.cfg
pretty_build-1.2.8.dist-info/LICENSE
pretty_build-1.2.8.dist-info/METADATA
pretty_build-1.2.8.dist-info/WHEEL
pretty_build-1.2.8.dist-info/entry_points.txt
pretty_build-1.2.8.dist-info/top_level.txt
pretty_build-1.2.8.dist-info/RECORD
