Metadata-Version: 2.1
Name: pretty-build
Version: 1.2.8
Summary: 增强型构建系统包装器 - 美观的构建界面和实时监控
Home-page: https://github.com/prettybuild/pretty-build
Author: Pretty Build Team
Author-email: team@prettybuild.dev
Project-URL: Bug Tracker, https://github.com/prettybuild/pretty-build/issues
Project-URL: Documentation, https://prettybuild.readthedocs.io/
Project-URL: Source Code, https://github.com/prettybuild/pretty-build
Keywords: build,cmake,make,tui,textual,monitoring,embedded,stm32
Classifier: Development Status :: 4 - Beta
Classifier: Intended Audience :: Developers
Classifier: Topic :: Software Development :: Build Tools
Classifier: Topic :: Software Development :: User Interfaces
Classifier: License :: OSI Approved :: MIT License
Classifier: Programming Language :: Python :: 3
Classifier: Programming Language :: Python :: 3.8
Classifier: Programming Language :: Python :: 3.9
Classifier: Programming Language :: Python :: 3.10
Classifier: Programming Language :: Python :: 3.11
Classifier: Programming Language :: Python :: 3.12
Classifier: Operating System :: OS Independent
Classifier: Environment :: Console
Classifier: Environment :: Console :: Curses
Requires-Python: >=3.8
License-File: LICENSE
Requires-Dist: rich >=13.0.0
Requires-Dist: textual >=0.41.0
Requires-Dist: click >=8.0.0
Requires-Dist: psutil >=5.9.0
Requires-Dist: plyer >=2.1.0
Requires-Dist: configparser >=5.3.0
Requires-Dist: pytest >=7.0.0
Requires-Dist: pytest-cov >=4.0.0
Requires-Dist: black >=22.0.0
Requires-Dist: flake8 >=5.0.0
Requires-Dist: mypy >=1.0.0
Provides-Extra: config
Requires-Dist: configparser >=5.0 ; extra == 'config'
Provides-Extra: dev
Requires-Dist: pytest >=6.0 ; extra == 'dev'
Requires-Dist: black >=21.0 ; extra == 'dev'
Requires-Dist: flake8 >=3.8 ; extra == 'dev'
Requires-Dist: mypy >=0.800 ; extra == 'dev'
Provides-Extra: notifications
Requires-Dist: plyer >=2.0 ; extra == 'notifications'
